{
  "version": 1,
  "tags": [
    {
      "name": "simple-image",
      "description": "`simple-image`\n\nAttributes:\n\n  * `src` {`string`} - image source\n\n  * `alt` {`string`} - alt data\n\n  * `caption` {`string`} - caption on the image\n\n  * `credit` {`string`} - photo credit / copyright info\n\n  * `schema-resource-id` {`string`} - Unique Resource ID, generated when schemaMap processes.\n\n  * `schemaMap` - Schema Map for the element, used to generate a valid prefix on the fly\nProps set for Polymer compatibility\n\nProperties:\n\n  * `src` {`string`} - image source\n\n  * `alt` {`string`} - alt data\n\n  * `caption` {`string`} - caption on the image\n\n  * `credit` {`string`} - photo credit / copyright info\n\n  * `schemaResourceID` {`string`} - Unique Resource ID, generated when schemaMap processes.\n\n  * `schemaMap` - Schema Map for the element, used to generate a valid prefix on the fly\nProps set for Polymer compatibility\n\n  * `_template` {`HTMLTemplateElement | null`} - \n\n  * `_importPath` {`string`} - \n\n  * `rootPath` {`string`} - \n\n  * `importPath` {`string`} - \n\n  * `root` {`HTMLElement | ShadowRoot | StampedTemplate | null`} - \n\n  * `$` - \n\n  * `_overrideLegacyUndefined` {`boolean`} - \n\n  * `PROPERTY_EFFECT_TYPES` - ",
      "attributes": [
        {
          "name": "src",
          "description": "`src` {`string`} - image source\n\nProperty: src"
        },
        {
          "name": "alt",
          "description": "`alt` {`string`} - alt data\n\nProperty: alt"
        },
        {
          "name": "caption",
          "description": "`caption` {`string`} - caption on the image\n\nProperty: caption"
        },
        {
          "name": "credit",
          "description": "`credit` {`string`} - photo credit / copyright info\n\nProperty: credit"
        },
        {
          "name": "schema-resource-id",
          "description": "`schema-resource-id` {`string`} - Unique Resource ID, generated when schemaMap processes.\n\nProperty: schemaResourceID\n\nDefault: "
        },
        {
          "name": "schemaMap",
          "description": "`schemaMap` - Schema Map for the element, used to generate a valid prefix on the fly\nProps set for Polymer compatibility\n\nProperty: schemaMap\n\nDefault: [object Object]"
        }
      ]
    },
    {
      "name": "simple-image",
      "description": "`simple-image`\n\nAttributes:\n\n  * `src` {`string`} - image source\n\n  * `alt` {`string`} - alt data\n\n  * `caption` {`string`} - caption on the image\n\n  * `credit` {`string`} - photo credit / copyright info\n\n  * `schema-resource-id` {`string`} - Unique Resource ID, generated when schemaMap processes.\n\n  * `schemaMap` - Schema Map for the element, used to generate a valid prefix on the fly\nProps set for Polymer compatibility\n\nProperties:\n\n  * `src` {`string`} - image source\n\n  * `alt` {`string`} - alt data\n\n  * `caption` {`string`} - caption on the image\n\n  * `credit` {`string`} - photo credit / copyright info\n\n  * `schemaResourceID` {`string`} - Unique Resource ID, generated when schemaMap processes.\n\n  * `schemaMap` - Schema Map for the element, used to generate a valid prefix on the fly\nProps set for Polymer compatibility\n\n  * `_template` {`HTMLTemplateElement | null`} - \n\n  * `_importPath` {`string`} - \n\n  * `rootPath` {`string`} - \n\n  * `importPath` {`string`} - \n\n  * `root` {`HTMLElement | ShadowRoot | StampedTemplate | null`} - \n\n  * `$` - \n\n  * `_overrideLegacyUndefined` {`boolean`} - \n\n  * `PROPERTY_EFFECT_TYPES` - ",
      "attributes": [
        {
          "name": "src",
          "description": "`src` {`string`} - image source\n\nProperty: src"
        },
        {
          "name": "alt",
          "description": "`alt` {`string`} - alt data\n\nProperty: alt"
        },
        {
          "name": "caption",
          "description": "`caption` {`string`} - caption on the image\n\nProperty: caption"
        },
        {
          "name": "credit",
          "description": "`credit` {`string`} - photo credit / copyright info\n\nProperty: credit"
        },
        {
          "name": "schema-resource-id",
          "description": "`schema-resource-id` {`string`} - Unique Resource ID, generated when schemaMap processes.\n\nProperty: schemaResourceID\n\nDefault: "
        },
        {
          "name": "schemaMap",
          "description": "`schemaMap` - Schema Map for the element, used to generate a valid prefix on the fly\nProps set for Polymer compatibility\n\nProperty: schemaMap\n\nDefault: [object Object]"
        }
      ]
    }
  ],
  "globalAttributes": [],
  "valueSets": []
}
