{
  "version": 1,
  "tags": [
    {
      "name": "qr-code",
      "description": "Properties:\n\n  * `windowControllers` - \n\n  * `_defineProperty` - ",
      "attributes": []
    },
    {
      "name": "q-r",
      "description": "`q-r`\n`Polymer wrapper for a qr code.`\n\nAttributes:\n\n  * `data` {`string`} - Data to code via QR code\n\n  * `title` {`string`} - Alternate title for the data\n\n  * `modulesize` {`number`} - module size of the square\n\n  * `margin` {`number`} - Margin on the square\n\n  * `format` {`string`} - format to output\n\nProperties:\n\n  * `data` {`string`} - Data to code via QR code\n\n  * `title` {`string`} - Alternate title for the data\n\n  * `modulesize` {`number`} - module size of the square\n\n  * `margin` {`number`} - Margin on the square\n\n  * `format` {`string`} - format to output",
      "attributes": [
        {
          "name": "data",
          "description": "`data` {`string`} - Data to code via QR code\n\nProperty: data"
        },
        {
          "name": "title",
          "description": "`title` {`string`} - Alternate title for the data\n\nProperty: title"
        },
        {
          "name": "modulesize",
          "description": "`modulesize` {`number`} - module size of the square\n\nProperty: modulesize\n\nDefault: 4"
        },
        {
          "name": "margin",
          "description": "`margin` {`number`} - Margin on the square\n\nProperty: margin\n\nDefault: 2"
        },
        {
          "name": "format",
          "description": "`format` {`string`} - format to output\n\nProperty: format\n\nDefault: png"
        }
      ]
    }
  ],
  "globalAttributes": [],
  "valueSets": []
}