{
  "version": 2,
  "tags": [
    {
      "name": "q-r\n`Polymer wrapper for a qr code.`",
      "description": "`q-r`",
      "jsDoc": "/**\n * `q-r`\n * @customElement q-r\n * `Polymer wrapper for a qr code.`\n *\n * @demo demo/index.html\n */",
      "attributes": [
        {
          "name": "data",
          "description": "Data to code via QR code",
          "jsDoc": "/**\n       * Data to code via QR code\n       */",
          "type": "string"
        },
        {
          "name": "title",
          "description": "Alternate title for the data",
          "jsDoc": "/**\n       * Alternate title for the data\n       */",
          "type": "string"
        },
        {
          "name": "modulesize",
          "description": "module size of the square",
          "jsDoc": "/**\n       * module size of the square\n       */",
          "type": "number"
        },
        {
          "name": "margin",
          "description": "Margin on the square",
          "jsDoc": "/**\n       * Margin on the square\n       */",
          "type": "number"
        },
        {
          "name": "format",
          "description": "format to output",
          "jsDoc": "/**\n       * format to output\n       */",
          "type": "string"
        }
      ],
      "properties": [
        {
          "name": "data",
          "description": "Data to code via QR code",
          "jsDoc": "/**\n       * Data to code via QR code\n       */",
          "type": "string"
        },
        {
          "name": "title",
          "description": "Alternate title for the data",
          "jsDoc": "/**\n       * Alternate title for the data\n       */",
          "type": "string"
        },
        {
          "name": "modulesize",
          "description": "module size of the square",
          "jsDoc": "/**\n       * module size of the square\n       */",
          "type": "number"
        },
        {
          "name": "margin",
          "description": "Margin on the square",
          "jsDoc": "/**\n       * Margin on the square\n       */",
          "type": "number"
        },
        {
          "name": "format",
          "description": "format to output",
          "jsDoc": "/**\n       * format to output\n       */",
          "type": "string"
        }
      ],
      "events": [],
      "slots": []
    },
    {
      "name": "q-r\n`Polymer wrapper for a qr code.`",
      "description": "`q-r`",
      "jsDoc": "/**\n * `q-r`\n * @customElement q-r\n * `Polymer wrapper for a qr code.`\n *\n * @demo demo/index.html\n */",
      "attributes": [
        {
          "name": "data",
          "description": "Data to code via QR code",
          "jsDoc": "/**\n       * Data to code via QR code\n       */",
          "type": "string"
        },
        {
          "name": "title",
          "description": "Alternate title for the data",
          "jsDoc": "/**\n       * Alternate title for the data\n       */",
          "type": "string"
        },
        {
          "name": "modulesize",
          "description": "module size of the square",
          "jsDoc": "/**\n       * module size of the square\n       */",
          "type": "number"
        },
        {
          "name": "margin",
          "description": "Margin on the square",
          "jsDoc": "/**\n       * Margin on the square\n       */",
          "type": "number"
        },
        {
          "name": "format",
          "description": "format to output",
          "jsDoc": "/**\n       * format to output\n       */",
          "type": "string"
        }
      ],
      "properties": [
        {
          "name": "data",
          "description": "Data to code via QR code",
          "jsDoc": "/**\n       * Data to code via QR code\n       */",
          "type": "string"
        },
        {
          "name": "title",
          "description": "Alternate title for the data",
          "jsDoc": "/**\n       * Alternate title for the data\n       */",
          "type": "string"
        },
        {
          "name": "modulesize",
          "description": "module size of the square",
          "jsDoc": "/**\n       * module size of the square\n       */",
          "type": "number"
        },
        {
          "name": "margin",
          "description": "Margin on the square",
          "jsDoc": "/**\n       * Margin on the square\n       */",
          "type": "number"
        },
        {
          "name": "format",
          "description": "format to output",
          "jsDoc": "/**\n       * format to output\n       */",
          "type": "string"
        }
      ],
      "events": [],
      "slots": []
    },
    {
      "name": "q-r\n`Polymer wrapper for a qr code.`",
      "description": "`q-r`",
      "jsDoc": "/**\n * `q-r`\n * @customElement q-r\n * `Polymer wrapper for a qr code.`\n *\n * @demo demo/index.html\n */",
      "attributes": [
        {
          "name": "data",
          "description": "Data to code via QR code",
          "jsDoc": "/**\n       * Data to code via QR code\n       */",
          "type": "string"
        },
        {
          "name": "title",
          "description": "Alternate title for the data",
          "jsDoc": "/**\n       * Alternate title for the data\n       */",
          "type": "string"
        },
        {
          "name": "modulesize",
          "description": "module size of the square",
          "jsDoc": "/**\n       * module size of the square\n       */",
          "type": "number"
        },
        {
          "name": "margin",
          "description": "Margin on the square",
          "jsDoc": "/**\n       * Margin on the square\n       */",
          "type": "number"
        },
        {
          "name": "format",
          "description": "format to output",
          "jsDoc": "/**\n       * format to output\n       */",
          "type": "string"
        }
      ],
      "properties": [
        {
          "name": "data",
          "description": "Data to code via QR code",
          "jsDoc": "/**\n       * Data to code via QR code\n       */",
          "type": "string"
        },
        {
          "name": "title",
          "description": "Alternate title for the data",
          "jsDoc": "/**\n       * Alternate title for the data\n       */",
          "type": "string"
        },
        {
          "name": "modulesize",
          "description": "module size of the square",
          "jsDoc": "/**\n       * module size of the square\n       */",
          "type": "number"
        },
        {
          "name": "margin",
          "description": "Margin on the square",
          "jsDoc": "/**\n       * Margin on the square\n       */",
          "type": "number"
        },
        {
          "name": "format",
          "description": "format to output",
          "jsDoc": "/**\n       * format to output\n       */",
          "type": "string"
        }
      ],
      "events": [],
      "slots": []
    }
  ]
}
