{
  "version": 1,
  "tags": [
    {
      "name": "simple-img",
      "description": "Attributes:\n\n  * `srcconverted` {`string | null`} - \n\n  * `rotate` {`string | null`} - \n\n  * `fit` {`string | null`} - \n\n  * `watermark` {`string | null`} - \n\n  * `wmspot` {`string | null`} - \n\n  * `format` {`string | null`} - \n\n  * `alt` {`string | null`} - \n\n  * `src` {`string | null`} - \n\n  * `loading` {`string | null`} - \n\n  * `decoding` {`string | null`} - \n\n  * `fetchpriority` {`string | null`} - \n\n  * `width` {`string | null`} - \n\n  * `height` {`string | null`} - \n\n  * `quality` {`string | null`} - \n\nProperties:\n\n  * `baseurl` {`string | null`} - \n\n  * `srcconverted` {`string | null`} - \n\n  * `rotate` {`string | null`} - \n\n  * `fit` {`string | null`} - \n\n  * `watermark` {`string | null`} - \n\n  * `wmspot` {`string | null`} - \n\n  * `format` {`string | null`} - \n\n  * `rendering` {`boolean`} - \n\n  * `alt` {`string | null`} - \n\n  * `src` {`string | null`} - \n\n  * `loading` {`string | null`} - \n\n  * `decoding` {`string | null`} - \n\n  * `fetchpriority` {`string | null`} - \n\n  * `width` {`string | null`} - \n\n  * `height` {`string | null`} - \n\n  * `innerHTML` - \n\n  * `quality` {`string | null`} - ",
      "attributes": [
        {
          "name": "srcconverted",
          "description": "`srcconverted` {`string | null`} - \n\nProperty: srcconverted",
          "values": []
        },
        {
          "name": "rotate",
          "description": "`rotate` {`string | null`} - \n\nProperty: rotate",
          "values": []
        },
        {
          "name": "fit",
          "description": "`fit` {`string | null`} - \n\nProperty: fit",
          "values": []
        },
        {
          "name": "watermark",
          "description": "`watermark` {`string | null`} - \n\nProperty: watermark",
          "values": []
        },
        {
          "name": "wmspot",
          "description": "`wmspot` {`string | null`} - \n\nProperty: wmspot",
          "values": []
        },
        {
          "name": "format",
          "description": "`format` {`string | null`} - \n\nProperty: format",
          "values": []
        },
        {
          "name": "alt",
          "description": "`alt` {`string | null`} - \n\nProperty: alt",
          "values": []
        },
        {
          "name": "src",
          "description": "`src` {`string | null`} - \n\nProperty: src",
          "values": []
        },
        {
          "name": "loading",
          "description": "`loading` {`string | null`} - \n\nProperty: loading",
          "values": []
        },
        {
          "name": "decoding",
          "description": "`decoding` {`string | null`} - \n\nProperty: decoding",
          "values": []
        },
        {
          "name": "fetchpriority",
          "description": "`fetchpriority` {`string | null`} - \n\nProperty: fetchpriority",
          "values": []
        },
        {
          "name": "width",
          "description": "`width` {`string | null`} - \n\nProperty: width",
          "values": []
        },
        {
          "name": "height",
          "description": "`height` {`string | null`} - \n\nProperty: height",
          "values": []
        },
        {
          "name": "quality",
          "description": "`quality` {`string | null`} - \n\nProperty: quality",
          "values": []
        }
      ]
    }
  ],
  "globalAttributes": [],
  "valueSets": []
}