{
  "canScale": true,
  "canPosition": true,
  "canEditSource": false,
  "gizmo": {
    "title": "Paper fab-transitions",
    "description": "Automated conversion of paper-fab-transitions/",
    "icon": "icons:android",
    "color": "green",
    "groups": ["Fab"],
    "handles": [
      {
        "type": "todo:read-the-docs-for-usage"
      }
    ],
    "meta": {
      "author": "btopro",
      "owner": "The Pennsylvania State University"
    }
  },
  "settings": {
    "quick": [],
    "configure": [],
    "advanced": []
  }
}
